JavaMianshiBiwenJvmKaodianJingjiangFix1/README.md
JavaMianshiBiwenJvmKaodianJingjiangFix1/__init__.py
JavaMianshiBiwenJvmKaodianJingjiangFix1/__main__.py
JavaMianshiBiwenJvmKaodianJingjiangFix1/file.epub
JavaMianshiBiwenJvmKaodianJingjiangFix1/index.html
JavaMianshiBiwenJvmKaodianJingjiangFix1/css/__init__.py
JavaMianshiBiwenJvmKaodianJingjiangFix1/css/annotations.css
JavaMianshiBiwenJvmKaodianJingjiangFix1/css/main.css
JavaMianshiBiwenJvmKaodianJingjiangFix1/css/normalize.css
JavaMianshiBiwenJvmKaodianJingjiangFix1/css/popup.css
JavaMianshiBiwenJvmKaodianJingjiangFix1/font/__init__.py
JavaMianshiBiwenJvmKaodianJingjiangFix1/font/fontello.eot
JavaMianshiBiwenJvmKaodianJingjiangFix1/font/fontello.svg
JavaMianshiBiwenJvmKaodianJingjiangFix1/font/fontello.ttf
JavaMianshiBiwenJvmKaodianJingjiangFix1/font/fontello.woff
JavaMianshiBiwenJvmKaodianJingjiangFix1/img/__init__.py
JavaMianshiBiwenJvmKaodianJingjiangFix1/img/annotator-glyph-sprite.png
JavaMianshiBiwenJvmKaodianJingjiangFix1/img/annotator-icon-sprite.png
JavaMianshiBiwenJvmKaodianJingjiangFix1/img/apple-touch-icon.png
JavaMianshiBiwenJvmKaodianJingjiangFix1/img/cancelfullscreen.png
JavaMianshiBiwenJvmKaodianJingjiangFix1/img/close.png
JavaMianshiBiwenJvmKaodianJingjiangFix1/img/fullscreen.png
JavaMianshiBiwenJvmKaodianJingjiangFix1/img/loader.gif
JavaMianshiBiwenJvmKaodianJingjiangFix1/img/menu-icon.png
JavaMianshiBiwenJvmKaodianJingjiangFix1/img/save.png
JavaMianshiBiwenJvmKaodianJingjiangFix1/img/saved.png
JavaMianshiBiwenJvmKaodianJingjiangFix1/img/settings-s.png
JavaMianshiBiwenJvmKaodianJingjiangFix1/img/settings.png
JavaMianshiBiwenJvmKaodianJingjiangFix1/img/star.png
JavaMianshiBiwenJvmKaodianJingjiangFix1/js/__init__.py
JavaMianshiBiwenJvmKaodianJingjiangFix1/js/epub.js
JavaMianshiBiwenJvmKaodianJingjiangFix1/js/epub.min.js
JavaMianshiBiwenJvmKaodianJingjiangFix1/js/epub.min.map
JavaMianshiBiwenJvmKaodianJingjiangFix1/js/hooks.min.js
JavaMianshiBiwenJvmKaodianJingjiangFix1/js/hooks.min.map
java_mianshi_biwen_jvm_kaodian_jingjiang_fix1-2025.3.25.0.dist-info/METADATA
java_mianshi_biwen_jvm_kaodian_jingjiang_fix1-2025.3.25.0.dist-info/WHEEL
java_mianshi_biwen_jvm_kaodian_jingjiang_fix1-2025.3.25.0.dist-info/entry_points.txt
java_mianshi_biwen_jvm_kaodian_jingjiang_fix1-2025.3.25.0.dist-info/top_level.txt
java_mianshi_biwen_jvm_kaodian_jingjiang_fix1-2025.3.25.0.dist-info/RECORD
